pyloric_network_simulator/_version.py
pyloric_network_simulator/jb_fixes.py
pyloric_network_simulator/prinz2004.py
pyloric_network_simulator/config/__init__.py
pyloric_network_simulator/config/defaults.cfg
pyloric_network_simulator/jax_shim/__init__.py
pyloric_network_simulator/jax_shim/numpy.py
pyloric_network_simulator/simresults/prinz2004_thermalize
pyloric_network_simulator-0.1.3.dist-info/licenses/LICENSE
pyloric_network_simulator-0.1.3.dist-info/METADATA
pyloric_network_simulator-0.1.3.dist-info/WHEEL
pyloric_network_simulator-0.1.3.dist-info/top_level.txt
pyloric_network_simulator-0.1.3.dist-info/RECORD
