Metadata-Version: 2.4
Name: pyloric-network-simulator
Version: 0.1.3
Summary: Pure-Python, JAX-accelerate implementation of the pyloric circuit model described by Prinz et al (Nat. Neurosci., 2004)
Author: Alexandre René
Maintainer: Alexandre René
License: MPL 2.0
Project-URL: Source, https://github.com/alcrene/pyloric-network-simulator
Keywords: simulation,computational-neuroscience,jax,pyloric-network
Classifier: Development Status :: 3 - Alpha
Classifier: Framework :: Jupyter :: JupyterLab
Classifier: Framework :: Jupyter :: JupyterLab :: 3
Classifier: Framework :: Jupyter :: JupyterLab :: 4
Classifier: Intended Audience :: Science/Research
Classifier: License :: OSI Approved :: Mozilla Public License 2.0 (MPL 2.0)
Classifier: Programming Language :: Python :: 3 :: Only
Classifier: Programming Language :: Python :: 3.9
Classifier: Programming Language :: Python :: 3.10
Classifier: Programming Language :: Python :: 3.11
Classifier: Topic :: Scientific/Engineering
Requires-Python: >=3.7
License-File: LICENSE
Requires-Dist: numpy
Requires-Dist: scipy
Requires-Dist: jax[cpu]
Requires-Dist: flufl.lock
Requires-Dist: addict
Requires-Dist: pandas
Requires-Dist: holoviews
Requires-Dist: scityping
Provides-Extra: docs
Requires-Dist: jupyter-book; extra == "docs"
Requires-Dist: jupytext; extra == "docs"
Requires-Dist: matplotlib; extra == "docs"
Requires-Dist: pint; extra == "docs"
Requires-Dist: watermark; extra == "docs"
Requires-Dist: ghp-import; extra == "docs"
Provides-Extra: test
Requires-Dist: pint; extra == "test"
Requires-Dist: holoviews; extra == "test"
Dynamic: license-file
